km3astro/__init__.py
km3astro/__version__.py
km3astro/constants.py
km3astro/coord.py
km3astro/extras.py
km3astro/frame.py
km3astro/io.py
km3astro/plot.py
km3astro/random.py
km3astro/sources.py
km3astro/testing_tools.py
km3astro/time.py
km3astro/toolbox.py
km3astro/data/orca_sun_isup.h5
km3astro/data/visibility_map_equatorial_antares.csv
km3astro/data/visibility_map_equatorial_antares.npy
km3astro/data/visibility_map_equatorial_arca.csv
km3astro/data/visibility_map_equatorial_orca.csv
km3astro/data/visibility_map_galactic_antares.csv
km3astro/data/visibility_map_galactic_antares.npy
km3astro/data/visibility_map_galactic_arca.csv
km3astro/data/visibility_map_galactic_orca.csv
km3astro/wip/__init__.py
km3astro/wip/below_horiz_orca.py
km3astro-0.17.0.dist-info/LICENSE
km3astro-0.17.0.dist-info/METADATA
km3astro-0.17.0.dist-info/WHEEL
km3astro-0.17.0.dist-info/top_level.txt
km3astro-0.17.0.dist-info/RECORD
