Metadata-Version: 2.1
Name: km3astro
Version: 0.17.0
Summary: Astronomical utilities for KM3NeT
Home-page: http://git.km3net.de/km3py/km3astro
Author: Tamas Gal and Moritz Lotze
Author-email: tgal@km3net.de
Platform: any
Classifier: Intended Audience :: Developers
Classifier: Intended Audience :: Science/Research
Classifier: Programming Language :: Python
Requires-Python: >=3.5
License-File: LICENSE
Requires-Dist: setuptools >=40.6.2
Requires-Dist: setuptools-scm
Requires-Dist: astropy >=3.0
Requires-Dist: matplotlib >=2.2
Requires-Dist: numpy
Requires-Dist: pandas
Requires-Dist: utm
Requires-Dist: healpy
Requires-Dist: km3io
Provides-Extra: dev
Requires-Dist: black ==22.3.0 ; extra == 'dev'
Requires-Dist: km3net-testdata >=0.4.13 ; extra == 'dev'
Requires-Dist: mock ; extra == 'dev'
Requires-Dist: numpydoc ; extra == 'dev'
Requires-Dist: pillow ; extra == 'dev'
Requires-Dist: pydocstyle ; extra == 'dev'
Requires-Dist: pytest ; extra == 'dev'
Requires-Dist: pytest-cov ; extra == 'dev'
Requires-Dist: pytest-flake8 ; extra == 'dev'
Requires-Dist: pytest-pylint ; extra == 'dev'
Requires-Dist: pytest-watch ; extra == 'dev'
Requires-Dist: sphinx-autoapi ; extra == 'dev'
Requires-Dist: sphinx-gallery ==0.10.1 ; extra == 'dev'
Requires-Dist: sphinx-rtd-theme >=0.3 ; extra == 'dev'
Requires-Dist: sphinx >=1.6.3 ; extra == 'dev'
Requires-Dist: sphinxcontrib-napoleon >=0.6.1 ; extra == 'dev'
Requires-Dist: sphinxcontrib-programoutput >=0.11 ; extra == 'dev'
Requires-Dist: sphinxcontrib-websupport >=1.0.1 ; extra == 'dev'
Requires-Dist: twine ; extra == 'dev'
Requires-Dist: utm ; extra == 'dev'
Requires-Dist: wheel ; extra == 'dev'
Provides-Extra: extras
Requires-Dist: pandas ; extra == 'extras'
Requires-Dist: ligo.skymap ; extra == 'extras'
